odoo8_addon_sale_order_calendar_event-8.0.1.0.0-py2.7-nspkg.pth
odoo_addons/sale_order_calendar_event/__openerp__.py
odoo_addons/sale_order_calendar_event/__init__.py
odoo_addons/sale_order_calendar_event/README.rst
odoo_addons/sale_order_calendar_event/models/sale_order.py
odoo_addons/sale_order_calendar_event/models/calendar_event.py
odoo_addons/sale_order_calendar_event/models/__init__.py
odoo_addons/sale_order_calendar_event/i18n/nl.po
odoo_addons/sale_order_calendar_event/views/sale_order.xml
odoo_addons/sale_order_calendar_event/views/menu.xml
odoo_addons/sale_order_calendar_event/views/calendar_event.xml
odoo_addons/sale_order_calendar_event/static/description/icon.png
odoo8_addon_sale_order_calendar_event-8.0.1.0.0.dist-info/top_level.txt
odoo8_addon_sale_order_calendar_event-8.0.1.0.0.dist-info/WHEEL
odoo8_addon_sale_order_calendar_event-8.0.1.0.0.dist-info/RECORD
odoo8_addon_sale_order_calendar_event-8.0.1.0.0.dist-info/metadata.json
odoo8_addon_sale_order_calendar_event-8.0.1.0.0.dist-info/DESCRIPTION.rst
odoo8_addon_sale_order_calendar_event-8.0.1.0.0.dist-info/METADATA
odoo8_addon_sale_order_calendar_event-8.0.1.0.0.dist-info/namespace_packages.txt
